vignette/__init__.py
vignette/__main__.py
vignette-5.1.1.dist-info/METADATA
vignette-5.1.1.dist-info/WHEEL
vignette-5.1.1.dist-info/entry_points.txt
vignette-5.1.1.dist-info/licenses/COPYING.WTFPL
vignette-5.1.1.dist-info/RECORD
