Metadata-Version: 2.1
Name: vignette
Version: 5.1.1
Summary: Library to create FreeDesktop-compatible thumbnails
Project-URL: Homepage, https://gitlab.com/hydrargyrum/vignette
Project-URL: Documentation, https://vignette.readthedocs.io/
Author-email: Hg <dev@indigo.re>
License-Expression: WTFPL
License-File: COPYING.WTFPL
Keywords: cache,freedesktop,image,thumbnail,thumbnails,xdg
Classifier: Development Status :: 4 - Beta
Classifier: Intended Audience :: Developers
Classifier: License :: Public Domain
Classifier: Programming Language :: Python :: 3
Classifier: Programming Language :: Python :: 3.6
Classifier: Programming Language :: Python :: 3.7
Classifier: Programming Language :: Python :: 3.8
Classifier: Programming Language :: Python :: 3.9
Classifier: Programming Language :: Python :: 3.10
Classifier: Programming Language :: Python :: 3.11
Classifier: Topic :: Desktop Environment
Classifier: Topic :: Multimedia :: Graphics
Classifier: Topic :: Software Development :: Libraries :: Python Modules
Classifier: Topic :: Utilities
Requires-Python: >=3.6
Requires-Dist: python-magic
Provides-Extra: pillow
Requires-Dist: pillow>=6.0; extra == 'pillow'
Provides-Extra: pyqt6
Requires-Dist: pyqt6; extra == 'pyqt6'
Provides-Extra: pythonmagick
Requires-Dist: pythonmagick; extra == 'pythonmagick'
